umo.cp37-win_amd64.pyd
umo-0.0.2.dist-info/METADATA
umo-0.0.2.dist-info/WHEEL
umo-0.0.2.dist-info/top_level.txt
umo-0.0.2.dist-info/RECORD
