Metadata-Version: 2.1
Name: umo
Version: 0.0.2
Summary: Modeler for mathematical programming solvers
Home-page: https://github.com/Coloquinte/umo
Author: Gabriel Gouvine
Author-email: gabriel.gouvine_umo@m4x.org
License: UNKNOWN
Platform: UNKNOWN
Classifier: Operating System :: POSIX :: Linux
Classifier: License :: OSI Approved :: MIT License
Classifier: Intended Audience :: Science/Research
Classifier: Intended Audience :: Developers
Classifier: Development Status :: 2 - Pre-Alpha
